databaseciservices/__init__.py
databaseciservices/call.py
databaseciservices/command.py
databaseciservices/conn.py
databaseciservices/copy.py
databaseciservices/do.py
databaseciservices/paging.py
databaseciservices/schema.py
databaseciservices/summary.py
databaseciservices/util.py
databaseciservices-6.0.0.dist-info/entry_points.txt
databaseciservices-6.0.0.dist-info/LICENSE.md
databaseciservices-6.0.0.dist-info/WHEEL
databaseciservices-6.0.0.dist-info/METADATA
databaseciservices-6.0.0.dist-info/RECORD
