Metadata-Version: 2.1
Name: databaseciservices
Version: 6.0.0
Summary: databaseci.com client
Home-page: https://databaseci.com
License: Fair Source License, version 0.9
Author: Robert Lechte
Author-email: rob@databaseci.com
Requires-Python: >=3.8,<4
Classifier: License :: Other/Proprietary License
Classifier: Programming Language :: Python :: 3
Classifier: Programming Language :: Python :: 3.8
Classifier: Programming Language :: Python :: 3.9
Classifier: Programming Language :: Python :: 3.10
Requires-Dist: click
Requires-Dist: migra
Requires-Dist: psycopg2-binary
Requires-Dist: py
Requires-Dist: pyyaml
Requires-Dist: requests
